fixture_magic/__init__.py
fixture_magic/compat.py
fixture_magic/utils.py
fixture_magic/management/__init__.py
fixture_magic/management/commands/__init__.py
fixture_magic/management/commands/custom_dump.py
fixture_magic/management/commands/dump_object.py
fixture_magic/management/commands/merge_fixtures.py
fixture_magic/management/commands/reorder_fixtures.py
tests/fixture_magic/__init__.py
tests/fixture_magic/test_utils.py
tests/fixture_magic/management/__init__.py
tests/fixture_magic/management/commands/__init__.py
tests/fixture_magic/management/commands/test_dump_object.py
django_fixture_magic-0.1.5.dist-info/LICENSE
django_fixture_magic-0.1.5.dist-info/METADATA
django_fixture_magic-0.1.5.dist-info/WHEEL
django_fixture_magic-0.1.5.dist-info/top_level.txt
django_fixture_magic-0.1.5.dist-info/RECORD
